{
  "persons": [

  ],
  "organizations": [

  ],
  "areas": [
    {
      "id": "Q180231",
      "identifiers": [
        {
          "scheme": "MS_FB",
          "identifier": "country:ie/county:kilkenny"
        },
        {
          "scheme": "wikidata",
          "identifier": "Q180231"
        }
      ],
      "associated_wikidata_positions": [
        "Q16152907",
        "Q54932485"
      ],
      "type": {
        "lang:en": "county of Ireland",
        "lang:ga": "Contaetha na hÉireann"
      },
      "name": {
        "lang:en": "Kilkenny County"
      },
      "parent_id": "Q27"
    },
    {
      "id": "Q27",
      "identifiers": [
        {
          "scheme": "MS_FB",
          "identifier": "country:ie"
        },
        {
          "scheme": "wikidata",
          "identifier": "Q27"
        }
      ],
      "associated_wikidata_positions": [
        "Q191827"
      ],
      "type": {
        "lang:en": "country"
      },
      "name": {
        "lang:en": "Republic of Ireland",
        "lang:ga": "Éire"
      },
      "parent_id": null
    }
  ],
  "memberships": [

  ]
}
